RKMVLogisticRegression/__init__.py
RKMVLogisticRegression/encrypted_logistic_regression.py
RKMVLogisticRegression-0.2.dist-info/LICENSE
RKMVLogisticRegression-0.2.dist-info/METADATA
RKMVLogisticRegression-0.2.dist-info/WHEEL
RKMVLogisticRegression-0.2.dist-info/top_level.txt
RKMVLogisticRegression-0.2.dist-info/RECORD
