Metadata-Version: 2.1
Name: RKMVLogisticRegression
Version: 0.2
Summary: A package for Encrypted Logistic Regression
Home-page: https://github.com/Me-Rajdip/RKMVLogisticRegression
Author: Rajdip Bera
Author-email: rajdipbera2002@gmail.com
License: UNKNOWN
Platform: UNKNOWN
Classifier: Programming Language :: Python :: 3
Classifier: License :: OSI Approved :: MIT License
Classifier: Operating System :: OS Independent
Requires-Python: >=3.6
License-File: LICENSE
Requires-Dist: numpy
Requires-Dist: scikit-learn
